fedwrap/__init__.py
fedwrap/cdc_brfss/__init__.py
fedwrap/cdc_brfss/brfss_utils.py
fedwrap/cdc_brfss/config.py
fedwrap/cdc_brfss/tools.py
fedwrap/cdc_places/__init__.py
fedwrap/cdc_places/config.py
fedwrap/cdc_places/places_utils.py
fedwrap/census_acs/DP02_functions.py
fedwrap/census_acs/DP03_functions.py
fedwrap/census_acs/DP04_functions.py
fedwrap/census_acs/DP05_functions.py
fedwrap/census_acs/__init__.py
fedwrap/census_acs/acs.py
fedwrap/census_acs/census_API_wrapper.py
fedwrap/widget/__init__.py
fedwrap/widget/explorer.py
fedwrap-1.0.4.dist-info/licenses/LICENSE
fedwrap-1.0.4.dist-info/METADATA
fedwrap-1.0.4.dist-info/WHEEL
fedwrap-1.0.4.dist-info/top_level.txt
fedwrap-1.0.4.dist-info/RECORD
