Metadata-Version: 2.4
Name: fedwrap
Version: 1.0.4
Summary: A library of API wrappers for US Federal Government datasets.
Author-email: Mark Aronson <mark.aronson@nih.gov>
License-Expression: MIT
Project-URL: Homepage, https://github.com/NIH-ScHARe/fedwrap
Project-URL: Issues, https://github.com/NIH-ScHARe/fedwrap/issues
Classifier: Programming Language :: Python :: 3
Classifier: Operating System :: OS Independent
Requires-Python: >=3.9
License-File: LICENSE
Requires-Dist: pandas
Requires-Dist: beautifulsoup4
Requires-Dist: requests
Requires-Dist: ipywidgets>=8.1.7
Dynamic: license-file
